XGB_Tuner/__init__.py
XGB_Tuner/main.py
tests/__init__.py
tests/test_tuner.py
xgboost_tuner_pack-0.1.5.dist-info/METADATA
xgboost_tuner_pack-0.1.5.dist-info/WHEEL
xgboost_tuner_pack-0.1.5.dist-info/entry_points.txt
xgboost_tuner_pack-0.1.5.dist-info/top_level.txt
xgboost_tuner_pack-0.1.5.dist-info/RECORD
