Metadata-Version: 2.4
Name: xgboost-tuner-pack
Version: 0.1.5
Summary: A hyperparameter tuner for XGBoost.
Home-page: https://github.com/AroopGit/XGB_Tuner
Author: Aroop
Author-email: work.arooprath@gmail.com
Keywords: xgboost tuner hyperparameter optimization
Classifier: Programming Language :: Python :: 3
Classifier: License :: OSI Approved :: MIT License
Classifier: Operating System :: OS Independent
Requires-Python: >=3.7
Requires-Dist: xgboost>=1.0
Requires-Dist: scikit-learn>=1.0
Requires-Dist: numpy>=1.17
Dynamic: author
Dynamic: author-email
Dynamic: classifier
Dynamic: description
Dynamic: description-content-type
Dynamic: home-page
Dynamic: keywords
Dynamic: requires-dist
Dynamic: requires-python
Dynamic: summary
